LICENSE.txt
MANIFEST.in
README.md
setup.cfg
setup.py
remeta/__init__.py
remeta/configuration.py
remeta/dist.py
remeta/fast_truncnorm.py
remeta/fit.py
remeta/gendata.py
remeta/model.py
remeta/modelspec.py
remeta/plot.py
remeta/transform.py
remeta/util.py
remeta.egg-info/PKG-INFO
remeta.egg-info/SOURCES.txt
remeta.egg-info/dependency_links.txt
remeta.egg-info/requires.txt
remeta.egg-info/top_level.txt
remeta/demo_data/example_data_criteria.pkl.gz
remeta/demo_data/example_data_criteria_levels.pkl.gz
remeta/demo_data/example_data_meta_add.pkl.gz
remeta/demo_data/example_data_meta_complex.pkl.gz
remeta/demo_data/example_data_meta_pow.pkl.gz
remeta/demo_data/example_data_meta_simple.pkl.gz
remeta/demo_data/example_data_noisy_readout.pkl.gz
remeta/demo_data/example_data_sens_complex.pkl.gz
remeta/demo_data/example_data_simple.pkl.gz