Metadata-Version: 2.1
Name: remeta
Version: 0.1.13
Summary: Reverse engineering of Metacognition toolbox
Author: Matthias Guggenmos
Author-email: mg.corresponding@gmail.com
Maintainer: Matthias Guggenmos
Maintainer-email: mg.corresponding@gmail.com
License: MIT License
Classifier: Development Status :: 4 - Beta
Classifier: License :: OSI Approved :: MIT License
Classifier: Programming Language :: Python :: 3
Classifier: Programming Language :: Python :: 3.6
Classifier: Programming Language :: Python :: 3.7
Classifier: Programming Language :: Python :: 3.8
Classifier: Programming Language :: Python :: 3.9
Classifier: Programming Language :: Python :: 3.10
Classifier: Programming Language :: Python :: 3.11
Classifier: Programming Language :: Python :: 3.12
Classifier: Programming Language :: Python :: 3.13
License-File: LICENSE.txt
Requires-Dist: numpy>=1.18.1
Requires-Dist: scipy>=1.3
Requires-Dist: multiprocessing_on_dill>=3.5.0a4
Requires-Dist: matplotlib>=3.1.3
